djangocms_page_image/__init__.py
djangocms_page_image/admin.py
djangocms_page_image/cms_plugins.py
djangocms_page_image/cms_toolbars.py
djangocms_page_image/models.py
djangocms_page_image/locale/de/LC_MESSAGES/django.mo
djangocms_page_image/locale/de/LC_MESSAGES/django.po
djangocms_page_image/migrations/0001_squashed_0007_auto_20170914_2241.py
djangocms_page_image/migrations/0008_add_ondelete.py
djangocms_page_image/migrations/0009_teaserextension.py
djangocms_page_image/migrations/0010_titleextension_data.py
djangocms_page_image/migrations/0011_childpageteasersplugin.py
djangocms_page_image/migrations/0012_remove_imageextension_teaser.py
djangocms_page_image/migrations/__init__.py
djangocms_page_image/templates/djangocms_page_image/menus/image_menu.html
djangocms_page_image/templates/djangocms_page_image/plugins/child_page_preview.html
djangocms_page_image/templates/djangocms_page_image/plugins/child_page_teasers.html
djangocms_page_image/templates/djangocms_page_image/plugins/sibling_page_preview.html
djangocms_page_image-0.7.1.dist-info/LICENSE
djangocms_page_image-0.7.1.dist-info/METADATA
djangocms_page_image-0.7.1.dist-info/WHEEL
djangocms_page_image-0.7.1.dist-info/top_level.txt
djangocms_page_image-0.7.1.dist-info/RECORD
