Metadata-Version: 2.1
Name: djangocms-page-image
Version: 0.7.1
Summary: django-cms page and title extensions providing image and teaser text
Home-page: http://github.com/febsn/djangocms-page-image
Author: Fabian Lehner
Author-email: fabian.lehner@marmara.at
License: MIT
Platform: UNKNOWN
Classifier: Development Status :: 3 - Alpha
Classifier: Framework :: Django
Classifier: Intended Audience :: Developers
Classifier: License :: OSI Approved :: MIT License
Classifier: Operating System :: OS Independent
Classifier: Programming Language :: Python
Classifier: Topic :: Internet :: WWW/HTTP
Requires-Dist: Django (>=1.11)
Requires-Dist: django-filer (>=1.2.0)
Requires-Dist: django-cms (>=3.5)
